libnxctrl/__init__.py
libnxctrl/backend.py
libnxctrl/joycontrol_wrapper.py
libnxctrl/nxbt_wrapper.py
libnxctrl/rpc.py
libnxctrl/splatplost_USB.py
libnxctrl/wrapper.py
libnxctrl/Poohl_joycontrol/LICENSE
libnxctrl/Poohl_joycontrol/README.md
libnxctrl/Poohl_joycontrol/joycontrol/__init__.py
libnxctrl/Poohl_joycontrol/joycontrol/command_line_interface.py
libnxctrl/Poohl_joycontrol/joycontrol/controller.py
libnxctrl/Poohl_joycontrol/joycontrol/controller_state.py
libnxctrl/Poohl_joycontrol/joycontrol/debug.py
libnxctrl/Poohl_joycontrol/joycontrol/device.py
libnxctrl/Poohl_joycontrol/joycontrol/logging_default.py
libnxctrl/Poohl_joycontrol/joycontrol/mcu.py
libnxctrl/Poohl_joycontrol/joycontrol/memory.py
libnxctrl/Poohl_joycontrol/joycontrol/my_semaphore.py
libnxctrl/Poohl_joycontrol/joycontrol/nfc_tag.py
libnxctrl/Poohl_joycontrol/joycontrol/protocol.py
libnxctrl/Poohl_joycontrol/joycontrol/report.py
libnxctrl/Poohl_joycontrol/joycontrol/server.py
libnxctrl/Poohl_joycontrol/joycontrol/transport.py
libnxctrl/Poohl_joycontrol/joycontrol/utils.py
libnxctrl/Poohl_joycontrol/joycontrol/profile/sdp_record_hid.xml
libnxctrl/mart1no_joycontrol/LICENSE
libnxctrl/mart1no_joycontrol/README.md
libnxctrl/mart1no_joycontrol/joycontrol/__init__.py
libnxctrl/mart1no_joycontrol/joycontrol/command_line_interface.py
libnxctrl/mart1no_joycontrol/joycontrol/controller.py
libnxctrl/mart1no_joycontrol/joycontrol/controller_state.py
libnxctrl/mart1no_joycontrol/joycontrol/device.py
libnxctrl/mart1no_joycontrol/joycontrol/logging_default.py
libnxctrl/mart1no_joycontrol/joycontrol/memory.py
libnxctrl/mart1no_joycontrol/joycontrol/protocol.py
libnxctrl/mart1no_joycontrol/joycontrol/report.py
libnxctrl/mart1no_joycontrol/joycontrol/server.py
libnxctrl/mart1no_joycontrol/joycontrol/transport.py
libnxctrl/mart1no_joycontrol/joycontrol/utils.py
libnxctrl/mart1no_joycontrol/joycontrol/profile/sdp_record_hid.xml
libnxctrl/nxbt/README.md
libnxctrl/nxbt/nxbt/__init__.py
libnxctrl/nxbt/nxbt/bluez.py
libnxctrl-0.2.1.dist-info/LICENSE
libnxctrl-0.2.1.dist-info/METADATA
libnxctrl-0.2.1.dist-info/WHEEL
libnxctrl-0.2.1.dist-info/top_level.txt
libnxctrl-0.2.1.dist-info/RECORD
